crypto_env/__init__.py
crypto_env/core.py
crypto_env/recorder.py
crypto_env/types.py
crypto_env/visualizer.py
crypto_env/algorithm/__init__.py
crypto_env/algorithm/algorithm.py
crypto_env/algorithm/buy_and_hold.py
crypto_env/algorithm/moving_average.py
crypto_env/dataloader/__init__.py
crypto_env/dataloader/dataloader.py
crypto_env/dataloader/ethloader.py
crenv-0.1.2.dist-info/METADATA
crenv-0.1.2.dist-info/WHEEL
crenv-0.1.2.dist-info/top_level.txt
crenv-0.1.2.dist-info/RECORD
